reahl/messages/reahl-paypalsupport
reahl/messages/af/LC_MESSAGES/reahl-paypalsupport.po
reahl/paypalsupport/__init__.py
reahl/paypalsupport/migrations.py
reahl/paypalsupport/paypalconfig.py
reahl/paypalsupport/paypallibrary.py
reahl/paypalsupport/paypalsupport.py
reahl/paypalsupport/reahl-paypalbuttonspanel.js
reahl_paypalsupport-7.0.3.dist-info/LICENSE
reahl_paypalsupport-7.0.3.dist-info/METADATA
reahl_paypalsupport-7.0.3.dist-info/WHEEL
reahl_paypalsupport-7.0.3.dist-info/entry_points.txt
reahl_paypalsupport-7.0.3.dist-info/reahl-component.toml
reahl_paypalsupport-7.0.3.dist-info/top_level.txt
reahl_paypalsupport-7.0.3.dist-info/RECORD
